near_py_tool
